numspark/__init__.py
numspark-1.2.dist-info/LICENSE
numspark-1.2.dist-info/METADATA
numspark-1.2.dist-info/WHEEL
numspark-1.2.dist-info/top_level.txt
numspark-1.2.dist-info/RECORD
