Metadata-Version: 2.1
Name: numspark
Version: 1.2
Summary: A math library for python
Home-page: https://github.com/Sahil-Rajwar-2004/NumSpark
Author: Sahil Rajwar
Project-URL: Source, https://github.com/Sahil-Rajwar-2004/NumSpark
Project-URL: Bug Reports, https://github.com/Sahil-Rajwar-2004/NumSpark/issues
Keywords: math library numpy-alternative sci-calc calc
Classifier: Development Status :: 5 - Production/Stable
Classifier: Intended Audience :: Developers
Classifier: License :: OSI Approved :: MIT License
Classifier: Programming Language :: Python :: 3
Classifier: Programming Language :: Python :: 3.7
Classifier: Programming Language :: Python :: 3.8
Classifier: Programming Language :: Python :: 3.9
License-File: LICENSE
Requires-Dist: numpy
Requires-Dist: sympy
